{
  "section_name": "4.4",
  "model_name": "lightgbm_tuned",
  "model_release_tag": "b4_15",
  "scoring_date_mode": "latest_available",
  "selected_scoring_date": "2020-10-31",
  "scoring_timestamp": "2026-04-21T13:46:42+00:00",
  "applied_threshold": 0.55,
  "record_count": 326,
  "station_count": 326,
  "positive_prediction_count": 303,
  "positive_prediction_share": 0.9294478527607362,
  "probability_min": 0.08219179511070251,
  "probability_mean": 0.7338902950286865,
  "probability_max": 0.9515119791030884,
  "prediction_summary_table": [
    {
      "model_name": "lightgbm_tuned",
      "model_release_tag": "b4_15",
      "selected_scoring_date": "2020-10-31T00:00:00",
      "scoring_timestamp": "2026-04-21T13:46:42+00:00",
      "record_count": 326,
      "positive_prediction_count": 303,
      "positive_prediction_share": 0.9294478527607362,
      "probability_min": 0.08219179511070251,
      "probability_mean": 0.7338902950286865,
      "probability_max": 0.9515119791030884,
      "applied_threshold": 0.55,
      "positive_class_label": "1",
      "prediction_ready_for_save": 1
    }
  ]
}